README.rst
setup.py
solver/__init__.py
solver.egg-info/PKG-INFO
solver.egg-info/SOURCES.txt
solver.egg-info/dependency_links.txt
solver.egg-info/top_level.txt
solver/arithmetic/__init__.py
solver/parsing/__init__.py
solver/parsing/parser.py
solver/test/__init__.py